nosqltangodb/__init__.py
nosqltangodb/__main__.py
nosqltangodb/_version.py
nosqltangodb/database.py
nosqltangodb/databaseds.py
nosqltangodb/db_errors.py
nosqltangodb/helper.py
nosqltangodb/db_access/__init__.py
nosqltangodb/db_access/_abstract.py
nosqltangodb/db_access/beacon.py
nosqltangodb/db_access/yaml.py
nosqltangodb/utils/__init__.py
nosqltangodb/utils/net_utils.py
nosqltangodb/utils/process_utils.py
nosqltangodb/utils/tango_utils.py
nosqltangodb-1.0.6.dist-info/licenses/LICENSE
nosqltangodb-1.0.6.dist-info/METADATA
nosqltangodb-1.0.6.dist-info/WHEEL
nosqltangodb-1.0.6.dist-info/entry_points.txt
nosqltangodb-1.0.6.dist-info/top_level.txt
nosqltangodb-1.0.6.dist-info/RECORD
