Metadata-Version: 2.4
Name: nosqltangodb
Version: 1.0.6
Summary: NoSQL in-memory Tango DB for project testing
Author-email: BLISS team <bliss@esrf.fr>
License: LGPLv3
Project-URL: Homepage, https://gitlab.esrf.fr/bliss/nosql-tango-db
Project-URL: Bug Tracker, https://gitlab.esrf.fr/bliss/nosql-tango-db/issues
Classifier: Programming Language :: Python :: 3
Classifier: License :: OSI Approved :: GNU Lesser General Public License v3 (LGPLv3)
Classifier: Operating System :: OS Independent
Requires-Python: >=3.8
License-File: LICENSE
Requires-Dist: pytango
Requires-Dist: ruamel.yaml
Requires-Dist: gevent
Requires-Dist: psutil
Provides-Extra: dev
Requires-Dist: black; extra == "dev"
Requires-Dist: pytest; extra == "dev"
Requires-Dist: types-PyYAML; extra == "dev"
Dynamic: license-file
